serialcables_hermes/__init__.py
serialcables_hermes/cli.py
serialcables_hermes/constants.py
serialcables_hermes/exceptions.py
serialcables_hermes/hermes.py
serialcables_hermes/models.py
serialcables_hermes/parsers.py
serialcables_hermes-0.1.0.dist-info/licenses/LICENSE
serialcables_hermes-0.1.0.dist-info/METADATA
serialcables_hermes-0.1.0.dist-info/WHEEL
serialcables_hermes-0.1.0.dist-info/entry_points.txt
serialcables_hermes-0.1.0.dist-info/top_level.txt
serialcables_hermes-0.1.0.dist-info/RECORD
