Metadata-Version: 2.4
Name: serialcables-hermes
Version: 0.1.0
Summary: Python API for Serial Cables PCIe Gen6 EDSFF Redriver Cards
Author-email: "Serial Cables, LLC" <support@serialcables.com>
Maintainer-email: "Serial Cables, LLC" <support@serialcables.com>
License-Expression: MIT
Project-URL: Homepage, https://www.serialcables.com
Project-URL: Documentation, https://github.com/serialcables/serialcables-hermes
Project-URL: Repository, https://github.com/serialcables/serialcables-hermes
Project-URL: Issues, https://github.com/serialcables/serialcables-hermes/issues
Keywords: pcie,gen6,redriver,edsff,nvme,ssd,serial-cables,hardware,test-equipment
Classifier: Development Status :: 4 - Beta
Classifier: Intended Audience :: Developers
Classifier: Intended Audience :: Science/Research
Classifier: Operating System :: OS Independent
Classifier: Programming Language :: Python :: 3
Classifier: Programming Language :: Python :: 3.9
Classifier: Programming Language :: Python :: 3.10
Classifier: Programming Language :: Python :: 3.11
Classifier: Programming Language :: Python :: 3.12
Classifier: Topic :: System :: Hardware
Classifier: Topic :: Scientific/Engineering
Classifier: Topic :: Software Development :: Libraries :: Python Modules
Requires-Python: >=3.9
License-File: LICENSE
Requires-Dist: pyserial>=3.5
Provides-Extra: dev
Requires-Dist: pytest>=7.0; extra == "dev"
Requires-Dist: pytest-cov>=4.0; extra == "dev"
Requires-Dist: black>=23.0; extra == "dev"
Requires-Dist: isort>=5.12; extra == "dev"
Requires-Dist: mypy>=1.0; extra == "dev"
Requires-Dist: ruff>=0.1.0; extra == "dev"
Dynamic: license-file
